simplegui2pygamemodule/__init__.py
simplegui2pygamemodule/simplegui2pygamemodule.py
simplegui2pygamemodule-1.0.3.dist-info/LICENCE.txt
simplegui2pygamemodule-1.0.3.dist-info/METADATA
simplegui2pygamemodule-1.0.3.dist-info/WHEEL
simplegui2pygamemodule-1.0.3.dist-info/top_level.txt
simplegui2pygamemodule-1.0.3.dist-info/RECORD
